[
    {
        "accuracy": 0.533,
        "batch_size": 5,
        "lr": 0.004099848063865428,
        "momentum": 0.4219324457431003,
        "transform": "cifar10_norm"
    },
    {
        "accuracy": 0.5208,
        "batch_size": 5,
        "lr": 0.005018537943573653,
        "momentum": 0.5380694650886741,
        "transform": "cifar10_norm"
    },
    {
        "accuracy": 0.5151,
        "batch_size": 5,
        "lr": 0.005959058000238111,
        "momentum": 0.15808996923548324,
        "transform": "cifar10_norm"
    },
    {
        "accuracy": 0.5124,
        "batch_size": 5,
        "lr": 0.006335065164379461,
        "momentum": 0.18858691390387777,
        "transform": "cifar10_norm"
    },
    {
        "accuracy": 0.5069,
        "batch_size": 8,
        "lr": 0.02014815717335616,
        "momentum": 0.09252715550629409,
        "transform": "cifar10_norm"
    },
    {
        "accuracy": 0.4867,
        "batch_size": 5,
        "lr": 0.009643131170202952,
        "momentum": 0.1462336697534524,
        "transform": "cifar10_norm"
    },
    {
        "accuracy": 0.4558,
        "batch_size": 4,
        "lr": 0.042358651296205904,
        "momentum": 0.16154719405120188,
        "transform": "cifar10_norm"
    },
    {
        "accuracy": 0.441,
        "batch_size": 16,
        "lr": 0.08384958267995807,
        "momentum": 0.5628037225557134,
        "transform": "cifar10_norm"
    },
    {
        "accuracy": 0.4334,
        "batch_size": 32,
        "lr": 0.1868905413326952,
        "momentum": 0.20380572044887071,
        "transform": "cifar10_norm"
    },
    {
        "accuracy": 0.4118,
        "batch_size": 5,
        "lr": 0.09398831411150982,
        "momentum": 0.2152560305429154,
        "transform": "cifar10_norm"
    },
    {
        "accuracy": 0.3814,
        "batch_size": 4,
        "lr": 0.12987490847955588,
        "momentum": 0.06294531031992666,
        "transform": "cifar10_norm"
    },
    {
        "accuracy": 0.3524,
        "batch_size": 32,
        "lr": 0.5818594420619727,
        "momentum": 0.016608952419416335,
        "transform": "cifar10_norm"
    },
    {
        "accuracy": 0.2846,
        "batch_size": 5,
        "lr": 0.22552447716260743,
        "momentum": 0.09212215449335133,
        "transform": "cifar10_norm"
    },
    {
        "accuracy": 0.2639,
        "batch_size": 5,
        "lr": 0.09652072816302458,
        "momentum": 0.3068221624938637,
        "transform": "cifar10_norm"
    },
    {
        "accuracy": 0.2634,
        "batch_size": 16,
        "lr": 0.17278613938597617,
        "momentum": 0.6855439114483798,
        "transform": "cifar10_norm"
    },
    {
        "accuracy": 0.2569,
        "batch_size": 5,
        "lr": 0.17992006250197906,
        "momentum": 0.33917618812219574,
        "transform": "cifar10_norm"
    },
    {
        "accuracy": 0.1874,
        "batch_size": 5,
        "lr": 0.3972182437507987,
        "momentum": 0.277888364955554,
        "transform": "cifar10_norm"
    },
    {
        "accuracy": 0.1553,
        "batch_size": 1,
        "lr": 0.5077465822066521,
        "momentum": 0.04531920182253427
    },
    {
        "accuracy": 0.1461,
        "batch_size": 5,
        "lr": 0.17332873797776766,
        "momentum": 0.4355313563851667,
        "transform": "cifar10_norm"
    },
    {
        "accuracy": 0.125,
        "batch_size": 8,
        "lr": 0.4604333536042966,
        "momentum": 0.030217389468858685,
        "transform": "cifar10_norm"
    },
    {
        "accuracy": 0.1,
        "batch_size": 4,
        "lr": 0.8100763440744065,
        "momentum": 0.2815042917995603,
        "transform": "cifar10_norm"
    },
    {
        "accuracy": 0.1,
        "batch_size": 8,
        "lr": 0.3003663088753863,
        "momentum": 0.058739942222160585,
        "transform": "cifar10_norm"
    },
    {
        "accuracy": 0.1,
        "batch_size": 4,
        "lr": 0.5851885327099468,
        "momentum": 0.2380066106555647,
        "transform": "cifar10_norm"
    },
    {
        "accuracy": 0.1,
        "batch_size": 5,
        "lr": 0.5155711021971213,
        "momentum": 0.019581180940027903,
        "transform": "cifar10_norm"
    },
    {
        "accuracy": 0.1,
        "batch_size": 16,
        "lr": 0.8543657743058846,
        "momentum": 0.125203998312189,
        "transform": "cifar10_norm"
    },
    {
        "accuracy": 0.1,
        "batch_size": 4,
        "lr": 0.8461207218786843,
        "momentum": 0.03002873984427924,
        "transform": "cifar10_norm"
    },
    {
        "accuracy": 0.1,
        "batch_size": 8,
        "lr": 0.28601935063784656,
        "momentum": 0.7299076869484438,
        "transform": "cifar10_norm"
    },
    {
        "accuracy": 0.1,
        "batch_size": 5,
        "lr": 0.2182654904124582,
        "momentum": 0.834454198241249,
        "transform": "cifar10_norm"
    },
    {
        "accuracy": 0.1,
        "batch_size": 5,
        "lr": 0.3609400159742866,
        "momentum": 0.4514499075485187,
        "transform": "cifar10_norm"
    },
    {
        "accuracy": 0.1,
        "batch_size": 16,
        "lr": 0.692583145519152,
        "momentum": 0.44342122886857077,
        "transform": "cifar10_norm"
    },
    {
        "accuracy": 0.1,
        "batch_size": 5,
        "lr": 0.12191542837063479,
        "momentum": 0.8655638357504857,
        "transform": "cifar10_norm"
    },
    {
        "accuracy": 0.1,
        "batch_size": 5,
        "lr": 0.9965401864746198,
        "momentum": 0.537136411650129,
        "transform": "cifar10_norm"
    },
    {
        "accuracy": 0.1,
        "batch_size": 5,
        "lr": 0.27843762527763205,
        "momentum": 0.011919791850667374,
        "transform": "cifar10_norm"
    }
]