[
    {
        "accuracy": 0.665,
        "batch": 4,
        "lr": 0.0061,
        "momentum": 0.7549,
        "duration": 2548855991468,
        "transform": "echo"
    },
    {
        "accuracy": 0.661,
        "batch": 4,
        "lr": 0.0061,
        "momentum": 0.7549,
        "duration": 2563443020063,
        "transform": "echo"
    },
    {
        "accuracy": 0.1,
        "batch": 1,
        "duration": 8994403272321,
        "lr": 0.8050334160352277,
        "momentum": 0.8963583102801932,
        "transform": "echo"
    }
]