[
    {
        "accuracy": 0.03604163974523544,
        "batch_size": 4,
        "lr": 2.7526642143444603e-05,
        "momentum": 0.4594784147793656,
        "transform": "echo"
    },
    {
        "accuracy": 0.0,
        "batch_size": 256,
        "lr": 0.003295102045699524,
        "momentum": 0.8328302556511478,
        "transform": "echo"
    },
    {
        "accuracy": 0.0,
        "batch_size": 512,
        "lr": 0.008278784881612003,
        "momentum": 0.9291830190586591,
        "transform": "echo"
    },
    {
        "accuracy": 0.0,
        "batch_size": 2,
        "lr": 0.007145183900860083,
        "momentum": 0.9301410758200124,
        "transform": "echo"
    },
    {
        "accuracy": 0.0,
        "batch_size": 16,
        "lr": 0.007235829731466351,
        "momentum": 0.9128519667197673,
        "transform": "echo"
    },
    {
        "accuracy": 0.0,
        "batch_size": 4,
        "lr": 0.00900823472337153,
        "momentum": 0.9526934548886203,
        "transform": "echo"
    },
    {
        "accuracy": 0.0,
        "batch_size": 8,
        "lr": 0.002737310238875917,
        "momentum": 0.8382401568156758,
        "transform": "echo"
    },
    {
        "accuracy": 0.0,
        "batch_size": 512,
        "lr": 0.00434732908215309,
        "momentum": 0.8081444374035682,
        "transform": "echo"
    },
    {
        "accuracy": 0.0,
        "batch_size": 4,
        "lr": 0.00539859881408898,
        "momentum": 0.9710213270894685,
        "transform": "echo"
    },
    {
        "accuracy": 0.0,
        "batch_size": 64,
        "lr": 0.007539623885765726,
        "momentum": 0.8078461933903556,
        "transform": "echo"
    },
    {
        "accuracy": 0.0,
        "batch_size": 1,
        "lr": 0.0016294103176750423,
        "momentum": 0.8150905343722831,
        "transform": "echo"
    },
    {
        "accuracy": 0.0,
        "batch_size": 256,
        "lr": 0.000218294993384556,
        "momentum": 0.8678891272585301,
        "transform": "echo"
    },
    {
        "accuracy": 0.0,
        "batch_size": 256,
        "lr": 0.004479278469012756,
        "momentum": 0.8760385070937465,
        "transform": "echo"
    },
    {
        "accuracy": 0.0,
        "batch_size": 1024,
        "lr": 0.008963006612692937,
        "momentum": 0.9048892054857187,
        "transform": "echo"
    },
    {
        "accuracy": 0.0,
        "batch_size": 128,
        "lr": 0.002615310927251158,
        "momentum": 0.8489809267452993,
        "transform": "echo"
    },
    {
        "accuracy": 0.0,
        "batch_size": 512,
        "lr": 0.005617504257975153,
        "momentum": 0.9885181136651718,
        "transform": "echo"
    },
    {
        "accuracy": 0.0,
        "batch_size": 2048,
        "lr": 0.0032956352590545134,
        "momentum": 0.9271942962015154,
        "transform": "echo"
    },
    {
        "accuracy": 0.0,
        "batch_size": 32,
        "lr": 0.0097368160791826,
        "momentum": 0.8888731717538813,
        "transform": "echo"
    },
    {
        "accuracy": 0.0,
        "batch_size": 4096,
        "lr": 0.006391772545886574,
        "momentum": 0.8375040204434168,
        "transform": "echo"
    },
    {
        "accuracy": 0.0,
        "batch_size": 256,
        "lr": 0.0012299559618375844,
        "momentum": 0.8691529946692996,
        "transform": "echo"
    },
    {
        "accuracy": 0.0,
        "batch_size": 512,
        "lr": 0.003766974430670826,
        "momentum": 0.9398699519497438,
        "transform": "echo"
    },
    {
        "accuracy": 0.0,
        "batch_size": 128,
        "lr": 0.008512353250967886,
        "momentum": 0.9010436305655911,
        "transform": "echo"
    },
    {
        "accuracy": 0.0,
        "batch_size": 2,
        "lr": 0.007315664415439878,
        "momentum": 0.9212577622977337,
        "transform": "echo"
    },
    {
        "accuracy": 0.0,
        "batch_size": 2,
        "lr": 0.006808239377435032,
        "momentum": 0.9471070569478994,
        "transform": "echo"
    },
    {
        "accuracy": 0.0,
        "batch_size": 2,
        "lr": 0.008170739463340505,
        "momentum": 0.9358128283071798,
        "transform": "echo"
    },
    {
        "accuracy": 0.0,
        "batch_size": 32,
        "lr": 0.005920992377991749,
        "momentum": 0.9653189061813217,
        "transform": "echo"
    },
    {
        "accuracy": 0.0,
        "batch_size": 1024,
        "lr": 0.007978326561181973,
        "momentum": 0.8885861039291681,
        "transform": "echo"
    },
    {
        "accuracy": 0.0,
        "batch_size": 4096,
        "lr": 0.009909444519818417,
        "momentum": 0.8528730360918335,
        "transform": "echo"
    },
    {
        "accuracy": 0.0,
        "batch_size": 1,
        "lr": 0.004960974603828055,
        "momentum": 0.8234227526339961,
        "transform": "echo"
    },
    {
        "accuracy": 0.0,
        "batch_size": 16,
        "lr": 0.006627031644933744,
        "momentum": 0.9213576425686679,
        "transform": "echo"
    },
    {
        "accuracy": 0.0,
        "batch_size": 64,
        "lr": 0.006062329763904759,
        "momentum": 0.9114074398854293,
        "transform": "echo"
    },
    {
        "accuracy": 0.0,
        "batch_size": 8,
        "lr": 0.007342987490137079,
        "momentum": 0.9664833403868262,
        "transform": "echo"
    },
    {
        "accuracy": 0.0,
        "batch_size": 16,
        "lr": 0.009126954651941672,
        "momentum": 0.9540640753024054,
        "transform": "echo"
    },
    {
        "accuracy": 0.0,
        "batch_size": 16,
        "lr": 0.008725229957056935,
        "momentum": 0.9123072073118057,
        "transform": "echo"
    },
    {
        "accuracy": 0.0,
        "batch_size": 512,
        "lr": 0.006835500825638954,
        "momentum": 0.9318729401669857,
        "transform": "echo"
    },
    {
        "accuracy": 0.0,
        "batch_size": 4,
        "lr": 0.007805051158749325,
        "momentum": 0.892045724249461,
        "transform": "echo"
    },
    {
        "accuracy": 0.0,
        "batch_size": 2048,
        "lr": 0.00442752323862229,
        "momentum": 0.9426085763231641,
        "transform": "echo"
    },
    {
        "accuracy": 0.0,
        "batch_size": 256,
        "lr": 0.0022381213078658613,
        "momentum": 0.9194490699667106,
        "transform": "echo"
    },
    {
        "accuracy": 0.0,
        "batch_size": 16,
        "lr": 0.005178457840508127,
        "momentum": 0.8795963187474698,
        "transform": "echo"
    },
    {
        "accuracy": 0.0,
        "batch_size": 2,
        "lr": 0.003830166173744796,
        "momentum": 0.9833835949367076,
        "transform": "echo"
    },
    {
        "accuracy": 0.0,
        "batch_size": 8,
        "lr": 0.009299147263538091,
        "momentum": 0.9587491473308772,
        "transform": "echo"
    },
    {
        "accuracy": 0.0,
        "batch_size": 512,
        "lr": 0.008326502797503606,
        "momentum": 0.8996082514154762,
        "transform": "echo"
    },
    {
        "accuracy": 0.0,
        "batch_size": 4,
        "lr": 0.007264842408005141,
        "momentum": 0.9475627699018732,
        "transform": "echo"
    },
    {
        "accuracy": 0.0,
        "batch_size": 4,
        "lr": 0.009289513283844867,
        "momentum": 0.9785602159018487,
        "transform": "echo"
    },
    {
        "accuracy": 0.0,
        "batch_size": 256,
        "lr": 0.007715329961319183,
        "momentum": 0.8028690493335272,
        "transform": "echo"
    },
    {
        "accuracy": 0.0,
        "batch_size": 4,
        "lr": 0.008513605855434715,
        "momentum": 0.9294874211948183,
        "transform": "echo"
    },
    {
        "accuracy": 0.0,
        "batch_size": 64,
        "lr": 0.0005858882461297022,
        "momentum": 0.9116317804130876,
        "transform": "echo"
    },
    {
        "accuracy": 0.0,
        "batch_size": 1,
        "lr": 0.009589369636825227,
        "momentum": 0.8199687008325091,
        "transform": "echo"
    },
    {
        "accuracy": 0.0,
        "batch_size": 512,
        "lr": 0.002390115262820319,
        "momentum": 0.960409496688817,
        "transform": "echo"
    },
    {
        "accuracy": 0.0,
        "batch_size": 256,
        "lr": 0.0030605166598289897,
        "momentum": 0.8347954369487377,
        "transform": "echo"
    },
    {
        "accuracy": 0.0,
        "batch_size": 128,
        "lr": 0.005553092514034637,
        "momentum": 0.863106294816412,
        "transform": "echo"
    },
    {
        "accuracy": 0.0,
        "batch_size": 1024,
        "lr": 0.008890110258254041,
        "momentum": 0.9759387216944643,
        "transform": "echo"
    },
    {
        "accuracy": 0.0,
        "batch_size": 8,
        "lr": 0.0016347951583829488,
        "momentum": 0.8333073749562598,
        "transform": "echo"
    },
    {
        "accuracy": 0.0,
        "batch_size": 8,
        "lr": 0.003441195998502349,
        "momentum": 0.8113062308287757,
        "transform": "echo"
    },
    {
        "accuracy": 0.0,
        "batch_size": 2,
        "lr": 0.0027666333267553508,
        "momentum": 0.8486380420239368,
        "transform": "echo"
    },
    {
        "accuracy": 0.0,
        "batch_size": 32,
        "lr": 0.004043190208241343,
        "momentum": 0.8407284213755417,
        "transform": "echo"
    },
    {
        "accuracy": 0.0,
        "batch_size": 4096,
        "lr": 0.004819761183359172,
        "momentum": 0.9377735791975019,
        "transform": "echo"
    },
    {
        "accuracy": 0.0,
        "batch_size": 2048,
        "lr": 0.00614499444436393,
        "momentum": 0.822184094386097,
        "transform": "echo"
    },
    {
        "accuracy": 0.0,
        "batch_size": 16,
        "lr": 0.001628294480942715,
        "momentum": 0.8562978522658773,
        "transform": "echo"
    },
    {
        "accuracy": 0.0,
        "batch_size": 512,
        "lr": 0.007025137566544739,
        "momentum": 0.8276785009619525,
        "transform": "echo"
    },
    {
        "accuracy": 0.0,
        "batch_size": 256,
        "lr": 0.008301857353808732,
        "momentum": 0.9197733471322305,
        "transform": "echo"
    },
    {
        "accuracy": 0.0,
        "batch_size": 8,
        "lr": 0.007911381063358794,
        "momentum": 0.9496549722121019,
        "transform": "echo"
    },
    {
        "accuracy": 0.0,
        "batch_size": 512,
        "lr": 0.004362645397450301,
        "momentum": 0.804850131732824,
        "transform": "echo"
    },
    {
        "accuracy": 0.0,
        "batch_size": 512,
        "lr": 0.0033920438841283087,
        "momentum": 0.8162442910805928,
        "transform": "echo"
    },
    {
        "accuracy": 0.0,
        "batch_size": 2,
        "lr": 0.003043947877084191,
        "momentum": 0.8435492910447078,
        "transform": "echo"
    },
    {
        "accuracy": 0.0,
        "batch_size": 4,
        "lr": 0.002011999501124881,
        "momentum": 0.9046435987161916,
        "transform": "echo"
    },
    {
        "accuracy": 0.0,
        "batch_size": 512,
        "lr": 0.0040864656380641875,
        "momentum": 0.8107124181896749,
        "transform": "echo"
    },
    {
        "accuracy": 0.0,
        "batch_size": 128,
        "lr": 0.006468275755048884,
        "momentum": 0.8002190911120584,
        "transform": "echo"
    },
    {
        "accuracy": 0.0,
        "batch_size": 16,
        "lr": 0.004690894330436349,
        "momentum": 0.9265611545285485,
        "transform": "echo"
    },
    {
        "accuracy": 0.0,
        "batch_size": 1,
        "lr": 0.00527509577517773,
        "momentum": 0.8801523675962457,
        "transform": "echo"
    },
    {
        "accuracy": 0.0,
        "batch_size": 2,
        "lr": 0.0075181768630563925,
        "momentum": 0.8955170822930882,
        "transform": "echo"
    },
    {
        "accuracy": 0.0,
        "batch_size": 1024,
        "lr": 0.009501932985453791,
        "momentum": 0.8287348741126043,
        "transform": "echo"
    },
    {
        "accuracy": 0.0,
        "batch_size": 4,
        "lr": 0.005769355291869166,
        "momentum": 0.9683823294904123,
        "transform": "echo"
    },
    {
        "accuracy": 0.0,
        "batch_size": 4,
        "lr": 0.006962771667692997,
        "momentum": 0.9340579687365163,
        "transform": "echo"
    },
    {
        "accuracy": 0.0,
        "batch_size": 64,
        "lr": 0.008635493734686493,
        "momentum": 0.9888779664281138,
        "transform": "echo"
    },
    {
        "accuracy": 0.0,
        "batch_size": 32,
        "lr": 0.0027518312814717944,
        "momentum": 0.9439826746540755,
        "transform": "echo"
    },
    {
        "accuracy": 0.0,
        "batch_size": 4,
        "lr": 0.0035635216642310435,
        "momentum": 0.9522449678437359,
        "transform": "echo"
    },
    {
        "accuracy": 0.0,
        "batch_size": 256,
        "lr": 0.008974871147336866,
        "momentum": 0.9247717353448158,
        "transform": "echo"
    },
    {
        "accuracy": 0.0,
        "batch_size": 4096,
        "lr": 0.0030582475346607315,
        "momentum": 0.9150631101404947,
        "transform": "echo"
    },
    {
        "accuracy": 0.0,
        "batch_size": 8,
        "lr": 0.005319366546039023,
        "momentum": 0.9711199343836509,
        "transform": "echo"
    },
    {
        "accuracy": 0.0,
        "batch_size": 16,
        "lr": 0.00803009758081164,
        "momentum": 0.9591999597693082,
        "transform": "echo"
    },
    {
        "accuracy": 0.0,
        "batch_size": 2048,
        "lr": 0.006247621158990742,
        "momentum": 0.8722618954641433,
        "transform": "echo"
    },
    {
        "accuracy": 0.0,
        "batch_size": 512,
        "lr": 0.007595598709344701,
        "momentum": 0.8108856297273964,
        "transform": "echo"
    },
    {
        "accuracy": 0.0,
        "batch_size": 64,
        "lr": 0.007243143800597198,
        "momentum": 0.8080662875127469,
        "transform": "echo"
    },
    {
        "accuracy": 0.0,
        "batch_size": 64,
        "lr": 0.006714387028460894,
        "momentum": 0.8171931542708162,
        "transform": "echo"
    },
    {
        "accuracy": 0.0,
        "batch_size": 64,
        "lr": 0.0038996256093761007,
        "momentum": 0.8277064069380283,
        "transform": "echo"
    },
    {
        "accuracy": 0.0,
        "batch_size": 4,
        "lr": 0.008232924942265086,
        "momentum": 0.9419116400078273,
        "transform": "echo"
    },
    {
        "accuracy": 0.0,
        "batch_size": 256,
        "lr": 0.007425630713804748,
        "momentum": 0.9816471289851433,
        "transform": "echo"
    },
    {
        "accuracy": 0.0,
        "batch_size": 2,
        "lr": 0.0042660575753222674,
        "momentum": 0.9339809106883054,
        "transform": "echo"
    },
    {
        "accuracy": 0.0,
        "batch_size": 512,
        "lr": 0.009981069372773987,
        "momentum": 0.8610484203531422,
        "transform": "echo"
    },
    {
        "accuracy": 0.0,
        "batch_size": 8,
        "lr": 0.0036683046189355402,
        "momentum": 0.8854956658330593,
        "transform": "echo"
    },
    {
        "accuracy": 0.0,
        "batch_size": 16,
        "lr": 0.007157003689610255,
        "momentum": 0.9085861974786514,
        "transform": "echo"
    },
    {
        "accuracy": 0.0,
        "batch_size": 1,
        "lr": 0.0012004197362864518,
        "momentum": 0.815058815360157,
        "transform": "echo"
    },
    {
        "accuracy": 0.0,
        "batch_size": 1,
        "lr": 0.0008963794555236016,
        "momentum": 0.807805274919882,
        "transform": "echo"
    },
    {
        "accuracy": 0.0,
        "batch_size": 1,
        "lr": 0.002361679280697928,
        "momentum": 0.8223367832478136,
        "transform": "echo"
    },
    {
        "accuracy": 0.0,
        "batch_size": 4,
        "lr": 0.008466526877282965,
        "momentum": 0.8335209562771664,
        "transform": "echo"
    },
    {
        "accuracy": 0.0,
        "batch_size": 128,
        "lr": 0.0017890263287707311,
        "momentum": 0.8003914920630782,
        "transform": "echo"
    },
    {
        "accuracy": 0.0,
        "batch_size": 1024,
        "lr": 0.00015093703101971877,
        "momentum": 0.9561275704472525,
        "transform": "echo"
    },
    {
        "accuracy": 0.0,
        "batch_size": 512,
        "lr": 0.007883547520655138,
        "momentum": 0.9643085781525035,
        "transform": "echo"
    },
    {
        "accuracy": 0.0,
        "batch_size": 256,
        "lr": 0.008869136912990416,
        "momentum": 0.8048699727756037,
        "transform": "echo"
    },
    {
        "accuracy": 0.0,
        "batch_size": 2,
        "lr": 0.0004853054357555559,
        "momentum": 0.8467424944122417,
        "transform": "echo"
    }
]